[{"s": "35-kilovatta-skolko-amper", "t": "3.5 кВт в амперах: расчёт для авто, дома и гаража (2026)", "i": "⚡", "c": "elektrika-avto"}, {"s": "350-gramm-vodki-cherez-skolko-mozhno-sest-za-rul", "t": "350 грамм водки: когда можно садиться за руль? Точные сроки 2026", "i": "⚖️", "c": "zakony-i-pdd"}, {"s": "35-metrov-v-sekundu-v-kilometry-v-chas-perevesti", "t": "35 м/с в км/ч: как перевести скорость автомобиля правильно", "i": "🎓", "c": "obuchenie-vozhdeniyu"}, {"s": "350-km-skolko-chasov-na-mashine-legkovoj-ekhat", "t": "350 км на машине: сколько времени ехать? Расчёт + советы водителям", "i": "🎓", "c": "obuchenie-vozhdeniyu"}, {"s": "35-en-v-rublyakh", "t": "35 евро в рублях: курс, конвертация и где выгоднее обменять в 2026", "i": "💰", "c": "finansy-avto"}, {"s": "350-gr-vodki-cherez-skolko-vyvetrivaetsya", "t": "350 г водки: время полного выветривания из организма", "i": "🛡️", "c": "bezopasnost"}, {"s": "35-kmch-v-ms", "t": "35 км/ч в м/с: точный перевод и физика движения", "i": "🎓", "c": "obuchenie-vozhdeniyu"}, {"s": "350-ml-vodki-cherez-skolko-vyvetrivaetsya", "t": "350 мл водки: через сколько выветривается из организма", "i": "🍷", "c": "voditel-i-zdorove"}, {"s": "35km-v-chas-v-metry-v-sekundu", "t": "35 км/ч в м/с: точный перевод и формула расчета", "i": "⚖️", "c": "zakony-i-pdd"}, {"s": "35-protsentov-ot-25000", "t": "35 процентов от 25000: точный расчет и примеры", "i": "💰", "c": "finansy-avto"}, {"s": "350-motochasov-eto-skolko-km", "t": "350 моточасов это сколько км: точный расчет ресурса", "i": "🚜", "c": "spetstekhnika-i-moto"}]