[{"s": "elm-eto-v-mashine", "t": "ELM327 в машине: что это, как подключить и настроить", "i": "📱", "c": "tekhnika-i-gadzhety"}, {"s": "elektronnyj-izmeritel-davleniya-v-shinakh", "t": "Электронный измеритель давления в шинах: как выбрать и пользоваться", "i": "📱", "c": "tekhnika-i-gadzhety"}, {"s": "elektronnyj-voltmetr-dlya-avtomobilya", "t": "Электронный вольтметр для авто: как выбрать и подключить правильно", "i": "⚡", "c": "elektrika-avto"}, {"s": "elm-327-chto-eto", "t": "ELM327: что это такое и как работает адаптер для диагностики авто", "i": "📱", "c": "tekhnika-i-gadzhety"}, {"s": "elektronnyj-pts-pri-pokupke-bu-avtomobilya", "t": "Электронный ПТС при покупке б/у авто: как проверить и оформить", "i": "📁", "c": null}, {"s": "elvira-povelitelnitsa-tmy-mashina", "t": "Эльвира Повелительница Тьмы: машина из фильма — секреты и факты", "i": "🎨", "c": "tyuning-i-stil"}, {"s": "elektromobil-kakoj-luchshe-vybrat", "t": "Какой электромобиль выбрать в 2026: рейтинг лучших моделей", "i": "📁", "c": null}, {"s": "elm-327-obd2-skaner-kak-rabotaet-i-na-chto-sposoben", "t": "ELM327 OBD2 сканер: как работает и на что способен в 2026 году", "i": "📱", "c": "tekhnika-i-gadzhety"}, {"s": "elektrozapravochnye-stantsii-dlya-elektromobilej", "t": "Электрозаправочные станции для электромобилей: виды, цены, установка", "i": "📱", "c": "tekhnika-i-gadzhety"}, {"s": "elektroavtomobil-s-samym-bolshim-zapasom-khoda", "t": "Электроавтомобили 2026: какой имеет самый большой запас хода?", "i": "📱", "c": "tekhnika-i-gadzhety"}, {"s": "elektromobil-gibrid-benzin-elektro", "t": "Гибриды и электромобили: что выбрать — бензин или электро?", "i": "📱", "c": "tekhnika-i-gadzhety"}, {"s": "elektromagnitnyj-klapan-dlya-posudomoechnoj-mashiny-bosch", "t": "Электромагнитный клапан для посудомоечной машины Bosch: выбор и ремонт", "i": "🏠", "c": "byt-i-khobbi"}, {"s": "elektromobil-gelendvagen-dlya-detej", "t": "Детский электромобиль Гелендваген: выбор, безопасность, обзор 2026", "i": "🏠", "c": "byt-i-khobbi"}, {"s": "elektronnyj-pts-na-avtomobil-kak-posmotret-vladeltsu", "t": "Как посмотреть электронный ПТС на автомобиль в 2026 году — пошаговая инструкция", "i": "⚖️", "c": "zakony-i-pdd"}, {"s": "elektricheskaya-skhema-avtomobilnogo-kompressora", "t": "Электрическая схема автокомпрессора: устройство и ремонт", "i": "⚡", "c": "elektrika-avto"}, {"s": "elektricheskij-lyuk-na-avtomobil", "t": "Электрический люк на автомобиль: виды, установка, цены 2026", "i": "🎨", "c": "tyuning-i-stil"}, {"s": "elektro-obzhimka-dlya-provodov", "t": "Электрообжимка для проводов: выбор, применение и секреты качественного обжима", "i": "⚡", "c": "elektrika-avto"}, {"s": "elektrodepo-vyborgskoe-peterburgskogo-metropolitena", "t": "Электродепо Выборгское: как работает сердце Петербургского метро", "i": "📜", "c": "istoriya-i-fakty"}, {"s": "elektroplita-podklyuchenie-k-seti-220", "t": "Подключение электроплиты к сети 220В: схема, правила, ошибки", "i": "🏗️", "c": "garazh-master"}, {"s": "elektrodvigatel-na-avtomobil-kupit", "t": "Электродвигатель для авто: как выбрать и купить правильно", "i": "🛢️", "c": "zapchasti-i-masla"}, {"s": "elektronnoe-svidetelstvo-o-registratsii-ts", "t": "Электронное свидетельство о регистрации ТС 2026: как получить и проверить", "i": "⚖️", "c": "zakony-i-pdd"}, {"s": "elektronnyj-pts-kak-kupit-avto-s-probegom", "t": "Электронный ПТС при покупке авто с пробегом: пошаговая инструкция 2026", "i": "📁", "c": null}, {"s": "elektroshchit-dlya-kvartiry-v-sbore", "t": "Электрощит для квартиры в сборе: цены, схемы и монтаж 2026", "i": "🏠", "c": "byt-i-khobbi"}, {"s": "elektronnyj-stoyanochnyj-tormoz-epb-s-funktsiej-brake-hold", "t": "Электронный стояночный тормоз EPB с функцией Brake Hold: как работает и зачем нужен", "i": "⚡", "c": "elektrika-avto"}, {"s": "elektroprovodka-na-kukhne-svoimi-rukami", "t": "Электропроводка на кухне своими руками: схема + пошаговая инструкция 2026", "i": "🏗️", "c": "garazh-master"}, {"s": "elm-chto-eto-takoe-v-avtomobile", "t": "ELM327 в автомобиле: что это, как работает и зачем нужен", "i": "⚡", "c": "elektrika-avto"}, {"s": "elektronnaya-massa-dlya-avtomobilya-12-volt", "t": "Электронная масса для авто 12В: выбор, подключение, ошибки", "i": "⚡", "c": "elektrika-avto"}, {"s": "elektroshchit-svoimi-rukami-dlya-kvartiry", "t": "Электрощит для квартиры своими руками: схема, монтаж, ошибки", "i": "🏗️", "c": "garazh-master"}, {"s": "elektro-kraskopulty-dlya-pokraski-avto", "t": "Электро краскопульты для покраски авто: выбор, настройка, ошибки", "i": "🔨", "c": "kuzovnoj-remont"}, {"s": "elektricheskie-soediniteli-provodov-vidy", "t": "Электрические соединители проводов: виды, применение, выбор", "i": "⚡", "c": "elektrika-avto"}, {"s": "elektroschetchik-na-stolbe-na-dache", "t": "Электросчетчик на столбе для дачи: правила установки и выбор модели", "i": "🏗️", "c": "garazh-master"}, {"s": "elektrodvigatel-na-koleso-avtomobilya", "t": "Электродвигатель на колесо: как работает и стоит ли ставить?", "i": "🎨", "c": "tyuning-i-stil"}, {"s": "elektronnyj-manometr-dlya-shin-kakoj-luchshe", "t": "Электронный манометр для шин 2026: какой лучше выбрать?", "i": "🛢️", "c": "zapchasti-i-masla"}, {"s": "elektromarkirovka-naklejki-dlya-elektroshchitov", "t": "Электромаркировка наклейки для щитов: требования и правила 2026", "i": "⚡", "c": "elektrika-avto"}, {"s": "elektromobili-kakie-est-marki", "t": "Электромобили 2026: ТОП-марок, цены, сравнение моделей", "i": "📱", "c": "tekhnika-i-gadzhety"}, {"s": "elektro-porogi-dlya-avto", "t": "Электропороги для авто: выбор, установка и преимущества (2026)", "i": "🎨", "c": "tyuning-i-stil"}, {"s": "elektrokary-s-bolshim-zapasom-khoda", "t": "Электрокары с большим запасом хода 2026: ТОП-10 моделей и советы по выбору", "i": "📱", "c": "tekhnika-i-gadzhety"}, {"s": "elektronnaya-muzyka-v-avto", "t": "Электронная музыка в авто: как настроить звук и выбрать оборудование", "i": "🎨", "c": "tyuning-i-stil"}, {"s": "elektronnyj-pts-chto-eto-i-kak-vyglyadit", "t": "Электронный ПТС 2026: что это, как выглядит и где получить", "i": "⚖️", "c": "zakony-i-pdd"}, {"s": "elektronnyj-pasport-ts-posmotret", "t": "Электронный паспорт ТС: как посмотреть и проверить онлайн", "i": "⚖️", "c": "zakony-i-pdd"}, {"s": "elementy-salona-avtomobilya-nazvaniya", "t": "Элементы салона автомобиля: названия и устройство", "i": "🧼", "c": "ukhod-i-mojka"}, {"s": "elektricheskie-porogi-dlya-avto", "t": "Электрические пороги для авто: выбор, установка и нюансы", "i": "🎨", "c": "tyuning-i-stil"}, {"s": "elektrokraskopult-dlya-pokraski-avtomobilya-kakoj-luchshe", "t": "Электрокраскопульт для авто: какой лучше выбрать для гаража", "i": "🔨", "c": "kuzovnoj-remont"}, {"s": "elektronnyj-pts-proverit-po-vin", "t": "Как проверить электронный ПТС по VIN: инструкция 2026", "i": "⚖️", "c": "zakony-i-pdd"}, {"s": "elektromobil-rossijskogo-proizvodstva-evolute", "t": "Evolute i-Joy и i-Pro: обзор российских электромобилей", "i": "📱", "c": "tekhnika-i-gadzhety"}, {"s": "elektronnyj-pts-na-avtomobil-posmotret-po-nomeru-avtomobilya-besplatno-onlajn", "t": "Электронный ПТС: как посмотреть по номеру авто бесплатно", "i": "⚖️", "c": "zakony-i-pdd"}, {"s": "elektronnaya-pts-na-avtomobil-chto-eto-takoe", "t": "Электронная ПТС на автомобиль: что это и как получить", "i": "⚖️", "c": "zakony-i-pdd"}, {"s": "elm327-instruktsiya-po-primeneniyu-na-russkom-yazyke", "t": "ELM327: Инструкция на русском языке. Настройка и подключение", "i": "📱", "c": "tekhnika-i-gadzhety"}, {"s": "elektroobogrevatel-dlya-garazha-220-volt", "t": "Электрообогреватель для гаража 220В: выбор и установка", "i": "🏗️", "c": "garazh-master"}, {"s": "elektromobil-raskhod-elektroenergii-na-100-km", "t": "Расход электроэнергии на 100 км электромобиля: реальные цифры", "i": "⚡", "c": "elektrika-avto"}, {"s": "elektro-avto-rossijskogo-proizvodstva", "t": "Электроавто РФ: обзор моделей, цен и господдержки", "i": "📁", "c": null}, {"s": "elastichnyj-shov-vruchnuyu-dlya-trikotazha", "t": "Эластичный шов для трикотажа: как сшить вручную", "i": "🏠", "c": "byt-i-khobbi"}, {"s": "elektroklemmy-dlya-soedineniya-provodov", "t": "Электроклеммы для проводов: виды, выбор и монтаж", "i": "🏗️", "c": "garazh-master"}, {"s": "elektronagnetatel-vozdukha-v-dvigatel", "t": "Электронагнетатель воздуха в двигатель: устройство и плюсы", "i": "🎨", "c": "tyuning-i-stil"}, {"s": "elektricheskij-nagnetatel-vozdukha-dlya-avtomobilya", "t": "Электрический нагнетатель воздуха для авто: Выбор и установка", "i": "🎨", "c": "tyuning-i-stil"}, {"s": "elektrodepo-avtovo-peterburgskogo-metropolitena", "t": "Электродепо Автово: история и техника Петербургского метро", "i": "🚜", "c": "spetstekhnika-i-moto"}, {"s": "elochka-pakhuchka-v-mashinu", "t": "Ёлочка-пахучка в машину: как выбрать, где вешать и чем заменить", "i": "🧼", "c": "ukhod-i-mojka"}, {"s": "elektronnye-torgi-po-bankrotstvu-avtomobili", "t": "Электронные торги по банкротству: как купить автомобиль", "i": "💰", "c": "finansy-avto"}, {"s": "elektroshchit-dlya-garazha-svoimi-rukami", "t": "Электрощит для гаража своими руками: схема и сборка", "i": "🏗️", "c": "garazh-master"}, {"s": "elm327-mini-instruktsiya-na-russkom", "t": "ELM327 Mini: подробная инструкция на русском языке", "i": "📱", "c": "tekhnika-i-gadzhety"}, {"s": "elm327-mini-kak-podklyuchit", "t": "ELM327 Mini: как подключить и настроить за 5 минут", "i": "📱", "c": "tekhnika-i-gadzhety"}, {"s": "elektricheskij-kraskopult-dlya-pokraski-avto-kakoj-luchshe", "t": "Какой электрический краскопульт для авто лучше: выбор и рейтинг", "i": "🔨", "c": "kuzovnoj-remont"}, {"s": "elm327-dlya-kakikh-mashin-podkhodit", "t": "ELM327 для каких машин подходит: полный список авто", "i": "📱", "c": "tekhnika-i-gadzhety"}, {"s": "elektricheskie-stantsii-dlya-zaryadki-avtomobilej", "t": "Электрические станции для зарядки авто: виды, выбор, установка", "i": "⚡", "c": "elektrika-avto"}, {"s": "elektrik-diagnost-avtomobilej-obuchenie", "t": "Электрик диагност автомобилей: обучение, курсы и перспективы", "i": "⚡", "c": "elektrika-avto"}, {"s": "elektro-vykhlop-na-mashinu", "t": "Электро выхлоп на машину: установка, виды и настройка звука", "i": "🎨", "c": "tyuning-i-stil"}, {"s": "elektronnyj-pasport-avtomobilya-posmotret", "t": "Электронный паспорт автомобиля: как посмотреть и проверить", "i": "⚖️", "c": "zakony-i-pdd"}, {"s": "elektronnyj-pts-na-pritsep-dlya-legkovogo-avtomobilya", "t": "Электронный ПТС на прицеп: оформление и нюансы", "i": "⚖️", "c": "zakony-i-pdd"}, {"s": "elektricheskij-kraskopult-dlya-pokraski-avtomobilya-kakoj-vybrat", "t": "Какой выбрать электрический краскопульт для авто: гид по моделям", "i": "🔨", "c": "kuzovnoj-remont"}, {"s": "elektromobil-s-solnechnymi-panelyami", "t": "Электромобиль с солнечными панелями: миф или реальность?", "i": "📱", "c": "tekhnika-i-gadzhety"}, {"s": "elektromobili-byd-vse-modeli", "t": "Все модели электромобилей BYD: характеристики и цены", "i": "📱", "c": "tekhnika-i-gadzhety"}, {"s": "elektromobili-v-19-veke", "t": "Электромобили в 19 веке: история и факты", "i": "📜", "c": "istoriya-i-fakty"}, {"s": "element-kuzova-avtomobilya-kotoryj-lyubit-gnit-4-bukvy-skanvord", "t": "Что гниет в авто на 4 буквы? Ответ на сканворд и защита кузова", "i": "🔨", "c": "kuzovnoj-remont"}, {"s": "elektrokary-s-samym-bolshim-zapasom-khoda", "t": "Электрокары с самым большим запасом хода: ТОП-10 моделей 2026", "i": "📱", "c": "tekhnika-i-gadzhety"}, {"s": "elektroskhemy-na-vse-avtomobili", "t": "Электросхемы автомобилей: поиск, чтение и расшифровка", "i": "⚡", "c": "elektrika-avto"}, {"s": "elektro-zaryadnaya-stantsiya-dlya-avtomobilya", "t": "Электрозарядная станция для автомобиля: выбор, монтаж и типы", "i": "⚡", "c": "elektrika-avto"}, {"s": "elektronnyj-pts-na-avto-gde-vzyat", "t": "Электронный ПТС: где получить и как оформить", "i": "⚖️", "c": "zakony-i-pdd"}, {"s": "elektrokar-s-samym-bolshim-zapasom-khoda", "t": "Электрокар с самым большим запасом хода: Топ-10 лидеров 2026 года", "i": "📱", "c": "tekhnika-i-gadzhety"}, {"s": "elektronnyj-pts-kak-eto-rabotaet", "t": "Электронный ПТС: как это работает, плюсы и минусы ЭПТС", "i": "⚖️", "c": "zakony-i-pdd"}, {"s": "elegans-avto-tsvetochnyj-proezd", "t": "Элеганс Авто Цветочный проезд: услуги, отзывы, контакты", "i": "🏗️", "c": "garazh-master"}, {"s": "elektronnyj-kompressor-dlya-avtomobilya", "t": "Электронный компрессор для авто: выбор и настройка", "i": "📱", "c": "tekhnika-i-gadzhety"}, {"s": "elektro-aromatizator-v-mashinu", "t": "Электро ароматизатор в машину: обзор, виды и выбор", "i": "🎨", "c": "tyuning-i-stil"}, {"s": "elektrody-dlya-svarki-kuzova-avtomobilya", "t": "Электроды для сварки кузова авто: выбор и технология", "i": "🔨", "c": "kuzovnoj-remont"}, {"s": "elektro-konditsioner-v-mashinu", "t": "Электро кондиционер в машину: выбор и монтаж автономного компрессора", "i": "⚡", "c": "elektrika-avto"}, {"s": "elektro-sidene-dlya-avto", "t": "Электро сиденье для авто: выбор, установка и ремонт", "i": "🎨", "c": "tyuning-i-stil"}, {"s": "elektronnyj-tekhpasport-avtomobilya-lichnyj-kabinet", "t": "Электронный техпаспорт: личный кабинет водителя в 2026 году", "i": "⚖️", "c": "zakony-i-pdd"}, {"s": "elm-eto-chto-v-mashine", "t": "ELM 327: что это в машине и как пользоваться адаптером", "i": "📱", "c": "tekhnika-i-gadzhety"}, {"s": "elektricheskij-turbonagnetatel-dlya-avtomobilya", "t": "Электрический турбонагнетатель: тюнинг авто без турбоямы", "i": "🎨", "c": "tyuning-i-stil"}, {"s": "elektronnyj-klyuch-dlya-avtomobilya-dublikat", "t": "Электронный ключ для автомобиля дубликат: изготовление и прошивка", "i": "⚡", "c": "elektrika-avto"}, {"s": "elektricheskaya-shlifovalnaya-mashinka-dlya-avto", "t": "Электрическая шлифовальная машинка для авто: выбор и применение", "i": "🔨", "c": "kuzovnoj-remont"}, {"s": "elektronnoe-svidetelstvo-o-registratsii-transportnogo-sredstva", "t": "Электронное СТС: как получить и проверить ЭПТС", "i": "⚖️", "c": "zakony-i-pdd"}, {"s": "elm-327-mini-kak-polzovatsya", "t": "ELM327 Mini: как пользоваться, подключать и настраивать", "i": "📱", "c": "tekhnika-i-gadzhety"}, {"s": "elektronnye-dokumenty-na-avtomobil-v-gosuslugakh", "t": "Электронные документы на автомобиль в Госуслугах: инструкция", "i": "⚖️", "c": "zakony-i-pdd"}, {"s": "elektronnaya-muzyka-v-mashinu-slushat-onlajn-besplatno", "t": "Электронная музыка в машину слушать онлайн бесплатно: гид по форматам", "i": "📱", "c": "tekhnika-i-gadzhety"}, {"s": "elektroprivod-sdvizhnoj-dveri-ador", "t": "Электропривод Ador для сдвижной двери: обзор и установка", "i": "🏗️", "c": "garazh-master"}, {"s": "elektronnyj-pasport-transportnogo-sredstva-kak-vyglyadit", "t": "Электронный ПТС: как выглядит образец и где найти", "i": "⚖️", "c": "zakony-i-pdd"}, {"s": "elvis-presli-i-polkovnik-parker", "t": "Элвис Пресли и Полковник Паркер: История великого союза", "i": "📜", "c": "istoriya-i-fakty"}, {"s": "elka-mashina-chto-za-marka", "t": "Елка машина: какая марка и как украсить авто", "i": "🎨", "c": "tyuning-i-stil"}, {"s": "elektricheskij-nasos-dlya-avtomobilya-220-volt", "t": "Электрический насос для автомобиля 220 вольт: выбор и применение", "i": "⚡", "c": "elektrika-avto"}, {"s": "elektroprivod-zerkal-chto-eto-takoe-v-mashine", "t": "Электропривод зеркал: что это, как работает и ремонт", "i": "⚡", "c": "elektrika-avto"}, {"s": "elektrousilitel-rulya-ustrojstvo-i-printsip-raboty", "t": "Электроусилитель руля: устройство, принцип работы и диагностика", "i": "⚡", "c": "elektrika-avto"}, {"s": "elektronnaya-sistema-kursovoj-ustojchivosti-esp", "t": "Система ESP: как работает, зачем нужна и можно ли отключать", "i": "🛡️", "c": "bezopasnost"}, {"s": "elektromobil-s-solnechnymi-batareyami", "t": "Электромобиль с солнечными батареями: миф или реальность?", "i": "📱", "c": "tekhnika-i-gadzhety"}, {"s": "elektrogenerator-dlya-chego-nuzhen", "t": "Электрогенератор для чего нужен: виды, выбор и применение", "i": "🏗️", "c": "garazh-master"}, {"s": "elektrousilitel-rulya-i-gidrousilitel-v-chem-raznitsa", "t": "Электроусилитель или гидроусилитель руля: сравнение, плюсы и минусы", "i": "🛢️", "c": "zapchasti-i-masla"}, {"s": "elf-wizard-pro-9", "t": "Elf Wizard Pro 9: Полный обзор, характеристики и возможности", "i": "📱", "c": "tekhnika-i-gadzhety"}, {"s": "elektromobil-evolyushn-rossijskogo-proizvodstva", "t": "Электромобиль Эволюшн российского производства: обзор и характеристики", "i": "📱", "c": "tekhnika-i-gadzhety"}, {"s": "elektrichka-sakharnyj-zavod-zip", "t": "Электричка Сахарный завод ЗИП: Расписание, остановки и маршрут", "i": "📁", "c": "drugoe"}, {"s": "elektrozamki-na-avtomobilnye-dveri", "t": "Электрозамки на авто: виды, установка, схемы подключения", "i": "⚡", "c": "elektrika-avto"}, {"s": "elektroshchit-vstroennyj-v-stenu", "t": "Встроенный электрощит в стену: монтаж, размеры и выбор", "i": "🏗️", "c": "garazh-master"}, {"s": "elektromotor-12-volt-moshchnyj-kupit", "t": "Мощный электромотор 12 Вольт: как выбрать и купить", "i": "⚡", "c": "elektrika-avto"}, {"s": "elektrooborudovanie-avtomobilya-ustrojstvo-i-printsip-raboty", "t": "Электрооборудование автомобиля: устройство и принцип работы систем", "i": "⚡", "c": "elektrika-avto"}, {"s": "elektrokar-syaomi-su-7", "t": "Xiaomi SU7: Обзор электрокара, характеристики и особенности", "i": "📱", "c": "tekhnika-i-gadzhety"}, {"s": "element-pelte-dlya-avtokholodilnika", "t": "Элемент Пельтье для автохолодильника: устройство, ремонт, замена", "i": "📱", "c": "tekhnika-i-gadzhety"}, {"s": "elektricheskaya-skhema-avtomobilnogo-generatora", "t": "Электрическая схема автомобильного генератора: устройство и ремонт", "i": "⚡", "c": "elektrika-avto"}, {"s": "elektronnaya-sts-na-avtomobil-gde-posmotret", "t": "Электронная СТС: где посмотреть и как получить", "i": "⚖️", "c": "zakony-i-pdd"}, {"s": "elpts-ru-elektronnyj-pts-na-mashinu", "t": "Электронный ПТС: как получить и проверить через elpts ru", "i": "⚖️", "c": "zakony-i-pdd"}, {"s": "elektronnyj-nasos-dlya-mashiny", "t": "Электронный насос для машины: выбор, установка, ремонт", "i": "📁", "c": null}, {"s": "elektronnyj-osvezhitel-vozdukha-dlya-avtomobilya", "t": "Электронный освежитель воздуха для авто: ТОП моделей и советы", "i": "📱", "c": "tekhnika-i-gadzhety"}, {"s": "elementy-kuzova-avtomobilya-v-kartinkakh", "t": "Элементы кузова автомобиля в картинках: полный справочник", "i": "🔨", "c": "kuzovnoj-remont"}, {"s": "elektrodvigatel-dlya-avtomobilya-kupit-gotovyj-komplekt", "t": "Электродвигатель для автомобиля: купить готовый комплект", "i": "🛢️", "c": "zapchasti-i-masla"}, {"s": "elektricheskij-gajkovert-dlya-kolesnykh-boltov", "t": "Электрический гайковерт для колесных болтов: выбор и применение", "i": "🏗️", "c": "garazh-master"}, {"s": "elm-327-bluetooth-avtoskaner-otzyvy", "t": "Elm 327 Bluetooth автосканер: отзывы, обзор программ и ошибки", "i": "📱", "c": "tekhnika-i-gadzhety"}]