[{"s": "hiace-perevod-na-russkij", "t": "Toyota Hiace: перевод названия, технические особенности и история модели", "i": "📜", "c": "istoriya-i-fakty"}, {"s": "hi-gear-shampun-dlya-beskontaktnoj-mojki-avtomobilya", "t": "Hi Gear шампунь для бесконтактной мойки: обзор и инструкция", "i": "🧼", "c": "ukhod-i-mojka"}, {"s": "high-power-puskovoe-ustrojstvo-ne-zaryazhaetsya", "t": "High power пусковое не заряжается: причины и ремонт", "i": "⚡", "c": "elektrika-avto"}, {"s": "high-temp-perevod-na-russkij", "t": "High Temp перевод на русский: расшифровка кодов ошибок в авто", "i": "📁", "c": null}, {"s": "hilux-perevod-na-russkij", "t": "Hilux перевод на русский: значение, история и характеристики", "i": "📜", "c": "istoriya-i-fakty"}, {"s": "hisense-chto-za-brend-otzyvy", "t": "Hisense: что за бренд и отзывы владельцев техники", "i": "📱", "c": "tekhnika-i-gadzhety"}, {"s": "high-power-puskovoe-ustrojstvo-kupit", "t": "High Power пусковое устройство: выбор и покупка бустера", "i": "📱", "c": "tekhnika-i-gadzhety"}, {"s": "hisense-otzyvy-o-brende", "t": "Hisense отзывы: стоит ли покупать? Честный анализ бренда", "i": "📱", "c": "tekhnika-i-gadzhety"}, {"s": "hi-fi-avtomobil-kitajskij", "t": "Китайский Hi-Fi звук в авто: выбор и установка", "i": "📱", "c": "tekhnika-i-gadzhety"}, {"s": "hiphi-z-120-kwh-2023", "t": "HiPhi Z 120 kWh 2023: характеристики и обзор электрокара", "i": "📱", "c": "tekhnika-i-gadzhety"}, {"s": "hisense-mashinka-stiralnaya-oshibka-f01", "t": "Hisense стиральная машина: ошибка F01 — как исправить", "i": "🏠", "c": "byt-i-khobbi"}]