[{"s": "spisok-marok-mashin-po-alfavitu", "t": "Список марок машин по алфавиту 2026: полный каталог + редкие бренды", "i": "📜", "c": "istoriya-i-fakty"}, {"s": "sportivnye-polosy-na-avto", "t": "Спортивные полосы на авто: виды, установка, законность в 2026 году", "i": "🎨", "c": "tyuning-i-stil"}, {"s": "sposob-postanovki-transportnogo-sredstva-na-stoyanku-na-kogo-rasprostranyaetsya", "t": "Кто обязан ставить машину на стоянку по правилам ПДД 2026? Полный разбор", "i": "⚖️", "c": "zakony-i-pdd"}, {"s": "spetsbuksir-gruzovaya-evakuatsiya-video", "t": "Спецбуксир для грузовой эвакуации: видео, цены, правила 2026", "i": "🚜", "c": "spetstekhnika-i-moto"}, {"s": "spisok-garazhej-pod-snos-v-spb", "t": "Список гаражей под снос в СПб 2026: актуальные данные и инструкции", "i": "🏗️", "c": "garazh-master"}, {"s": "sprej-ot-zapotevaniya-stekol-avtomobilya", "t": "Спрей от запотевания стекол в машине: как выбрать и использовать", "i": "🧼", "c": "ukhod-i-mojka"}, {"s": "spisok-tovarov-dlya-parallelnogo-importa", "t": "Список товаров для параллельного импорта в 2026: что можно ввозить легально", "i": "🛢️", "c": "zapchasti-i-masla"}, {"s": "spat-v-mashine-v-puteshestvii", "t": "Как спать в машине в путешествии: безопасно и комфортно", "i": "🛡️", "c": "bezopasnost"}, {"s": "sportivnyj-shov-na-rule", "t": "Спортивный шов на руле: как выбрать, установить и ухаживать", "i": "🎨", "c": "tyuning-i-stil"}, {"s": "spalnik-na-kryshu-avto", "t": "Спальник на крышу авто: как выбрать и установить правильно", "i": "🎨", "c": "tyuning-i-stil"}, {"s": "spetsialnaya-mashina-s-chernym-krestom", "t": "Машина с черным крестом: назначение, правила и особенности", "i": "🚜", "c": "spetstekhnika-i-moto"}, {"s": "spisok-marok-avtomobilej-po-alfavitu", "t": "Список марок автомобилей по алфавиту 2026: полный каталог + редкие бренды", "i": "📜", "c": "istoriya-i-fakty"}, {"s": "sposoby-soedineniya-odnozhilnykh-provodov", "t": "Как соединить одножильные провода: 7 проверенных способов", "i": "⚡", "c": "elektrika-avto"}, {"s": "sportloto-84-sledstvie-veli", "t": "Спортлото 84: следствие великого розыгрыша — разбор скандала 1984 года", "i": "📜", "c": "istoriya-i-fakty"}, {"s": "sposobnost-aktivov-byt-bystro-prodannymi-po-tsene-blizkoj-k-rynochnoj", "t": "Ликвидность активов: как быстро продать авто по рыночной цене", "i": "💰", "c": "finansy-avto"}, {"s": "spisok-dokumentov-dlya-postanovki-na-uchet-novogo-avtomobilya", "t": "Документы для регистрации нового авто в 2026: полный список и нюансы", "i": "⚖️", "c": "zakony-i-pdd"}, {"s": "spisok-oborudovaniya-dlya-avtoservisa", "t": "Оборудование для автосервиса: полный список 2026 года", "i": "🏗️", "c": "garazh-master"}, {"s": "sposoby-soedineniya-mednykh-provodov-mezhdu-soboj", "t": "Как соединить медные провода: 7 проверенных способов для авто", "i": "⚡", "c": "elektrika-avto"}, {"s": "sportivnye-mashiny-do-5-millionov", "t": "Спортивные машины до 5 млн рублей: ТОП-10 моделей 2026-2026", "i": "📁", "c": null}, {"s": "spusknik-vozdukha-sistemy-okhlazhdeniya-avtomobilya", "t": "Спускник воздуха в системе охлаждения: как правильно стравить воздух", "i": "📁", "c": null}, {"s": "spets-nomera-na-avtomobil", "t": "Спецномера на автомобиль: как получить, стоимость, законы 2026", "i": "⚖️", "c": "zakony-i-pdd"}, {"s": "spyat-mashiny-v-garazhe-kolybelnaya", "t": "Спят машины в гараже: колыбельная для авто и 7 правил зимней консервации", "i": "🏗️", "c": "garazh-master"}, {"s": "spalnik-v-avtobuse-dlya-voditelya", "t": "Спальник для водителя в автобусе: как выбрать и установить (2026)", "i": "🛡️", "c": "bezopasnost"}, {"s": "sportivnye-mashiny-marki-nedorogie", "t": "Топ-10 недорогих спортивных машин: цены, характеристики, советы по выбору", "i": "📁", "c": null}, {"s": "sputnikovaya-okhrannaya-sistema-dlya-avtomobilya", "t": "Спутниковая охрана для авто: как выбрать и установить в 2026 году", "i": "🛡️", "c": "bezopasnost"}, {"s": "spisok-umnykh-slov-i-ikh-znacheniya", "t": "Умные слова для автолюбителей: 100+ терминов с расшифровкой 2026", "i": "📁", "c": "drugoe"}, {"s": "spravka-schet-na-dvigatel", "t": "Справка-счет на двигатель: как оформить, где получить, образец 2026", "i": "🛢️", "c": "zapchasti-i-masla"}, {"s": "spisok-parallelnogo-importa-2025", "t": "Параллельный импорт 2026: полный список автомобилей и правила ввоза", "i": "⚖️", "c": "zakony-i-pdd"}, {"s": "spravka-o-chlenstve-v-garazhnom-kooperative-obrazets", "t": "Справка о членстве в гаражном кооперативе: образец 2026 и инструкция", "i": "🏗️", "c": "garazh-master"}, {"s": "sprej-antigravij-dlya-avto", "t": "Антигравийный спрей для авто: как выбрать и нанести правильно", "i": "🔨", "c": "kuzovnoj-remont"}, {"s": "sprej-ot-myshej-i-krys", "t": "Спрей от мышей и крыс: как выбрать и применять в гараже и доме", "i": "🏗️", "c": "garazh-master"}, {"s": "spisok-transformerov-iz-filma", "t": "Трансформеры из фильма: полный список персонажей и их особенности", "i": "📜", "c": "istoriya-i-fakty"}, {"s": "spisok-zapreshchennykh-lekarstvennykh-preparatov-dlya-voditelej", "t": "Запрещённые лекарства для водителей 2026: полный список и штрафы", "i": "🍷", "c": "voditel-i-zdorove"}, {"s": "spetsialist-po-sobakam-7-bukv", "t": "Кинолог — кто это? Специалист по собакам из 7 букв", "i": "🏠", "c": "byt-i-khobbi"}, {"s": "spets-antenny-na-avto", "t": "Спец антенны для авто: выбор, установка и настройка в 2026 году", "i": "🎨", "c": "tyuning-i-stil"}, {"s": "spisok-amr-97-vladeltsev", "t": "АМР-97: как найти владельцев по номеру — законные способы 2026", "i": "🚜", "c": "spetstekhnika-i-moto"}, {"s": "spi-spokojno-strana-tekst", "t": "«Спи спокойно, страна»: текст гимна СССР и его история", "i": "📜", "c": "istoriya-i-fakty"}, {"s": "spisok-motornykh-masel-dlya-avtomobilej", "t": "Топ-10 моторных масел 2026: рейтинг для бензиновых и дизельных ДВС", "i": "🛢️", "c": "zapchasti-i-masla"}, {"s": "sportivnye-mashiny-na-avtomate", "t": "Спортивные машины на автомате: плюсы, минусы и лучшие модели 2026", "i": "🎨", "c": "tyuning-i-stil"}, {"s": "sposoby-vosstanovleniya-elementov-kuzova", "t": "Восстановление кузова автомобиля: 7 проверенных способов (2026)", "i": "🔨", "c": "kuzovnoj-remont"}, {"s": "spu-chto-eto-takoe", "t": "СПУ в автомобиле — что это, как работает и зачем нужно", "i": "🛡️", "c": "bezopasnost"}, {"s": "spas-odeyalo-kakoj-storonoj", "t": "Спас-одеяло: какой стороной укладывать в машине? Правила и ошибки", "i": "🛡️", "c": "bezopasnost"}, {"s": "spb-ruskeala-rasstoyanie-na-mashine", "t": "Расстояние СПб → Рускеала на машине: маршруты, время, советы 2026", "i": "🏗️", "c": "garazh-master"}, {"s": "spisok-luchshikh-gonok-na-pk", "t": "Топ-15 гонок на ПК в 2026: реализм, аркады и симуляторы", "i": "📱", "c": "tekhnika-i-gadzhety"}, {"s": "spalnyj-meshok-outventure-yukon-6", "t": "Спальный мешок Outventure Yukon 6: обзор, характеристики и советы по выбору", "i": "🏠", "c": "byt-i-khobbi"}, {"s": "spidometr-avtomobilya-ne-pokazyvaet-skorost-prichiny", "t": "Спидометр не работает: 7 причин и как устранить неисправность", "i": "⚡", "c": "elektrika-avto"}, {"s": "spalnik-na-kryshu-gruzovika", "t": "Спальник на крышу грузовика: выбор, установка и безопасность", "i": "🎨", "c": "tyuning-i-stil"}, {"s": "spidometr-chto-eto-takoe-v-mashine", "t": "Спидометр в машине: что это, как работает и почему врет", "i": "📱", "c": "tekhnika-i-gadzhety"}, {"s": "sportkar-eto-kakaya-mashina", "t": "Спортивный автомобиль: что это за машина и как выбрать", "i": "📁", "c": null}, {"s": "spisok-radiostantsij-fm-diapazona", "t": "FM-радиостанции в машине: полный список и настройка 2026", "i": "📱", "c": "tekhnika-i-gadzhety"}, {"s": "spalnoe-mesto-na-kryshe-avtomobilya", "t": "Спальное место на крыше авто: как выбрать и установить (2026)", "i": "🎨", "c": "tyuning-i-stil"}, {"s": "spokojnye-treki-v-mashinu", "t": "Спокойные треки в машину: плейлист для комфортной езды 2026", "i": "🍷", "c": "voditel-i-zdorove"}, {"s": "sportivnye-mashiny-do-2-millionov", "t": "Спортивные машины до 2 млн рублей: ТОП-10 моделей 2026-2026", "i": "📁", "c": null}, {"s": "spektaklya-ne-budet-my-opisali-rekvizit", "t": "«Спектакля не будет»: как описать реквизит для продажи авто — советы эксперта", "i": "🛢️", "c": "zapchasti-i-masla"}, {"s": "spitsevye-diski-na-mashinu", "t": "Спицевые диски на машину: плюсы, минусы и выбор (2026)", "i": "🎨", "c": "tyuning-i-stil"}, {"s": "spravka-ob-otsenke-avtomobilya", "t": "Справка об оценке автомобиля 2026: где получить и зачем нужна", "i": "💰", "c": "finansy-avto"}, {"s": "spalnyj-matras-v-mashinu", "t": "Спальный матрас в машину: как выбрать и установить правильно", "i": "🏠", "c": "byt-i-khobbi"}, {"s": "spek-eto-v-avtomobile", "t": "СПЕК в автомобиле: что это, как проверить и исправить ошибки", "i": "⚡", "c": "elektrika-avto"}, {"s": "sputnik-v-mashine-eto", "t": "Спутник в машине: что это и зачем нужен в 2026 году", "i": "📱", "c": "tekhnika-i-gadzhety"}, {"s": "spisok-dokumentov-dlya-registratsii-ts", "t": "Список документов для регистрации ТС: полный гайд 2026-2026", "i": "⚖️", "c": "zakony-i-pdd"}, {"s": "spustili-kolesa-na-mashine-otvetstvennost", "t": "Спустили колеса: ответственность, штрафы и что делать", "i": "⚖️", "c": "zakony-i-pdd"}, {"s": "spisok-avto-e-klassa", "t": "Список авто E-класса: рейтинг моделей и сравнение", "i": "📁", "c": null}, {"s": "spisok-tabletok-kotorye-nelzya-pit-za-rulem", "t": "Список таблеток, которые нельзя пить за рулем: полный список препаратов", "i": "🛡️", "c": "bezopasnost"}, {"s": "splitter-eto-na-mashine", "t": "Сплиттер на машине: зачем нужен, как работает и стоит ли ставить", "i": "🎨", "c": "tyuning-i-stil"}, {"s": "spitsovannye-diski-na-avto", "t": "Спицованные диски: плюсы, минусы и выбор для авто", "i": "🎨", "c": "tyuning-i-stil"}, {"s": "spetsialnoe-uderzhivayushchee-ustrojstvo-dlya-perevozki-detej-ot-7-do-12", "t": "Перевозка детей 7-12 лет: выбор и установка удерживающего устройства", "i": "⚖️", "c": "zakony-i-pdd"}, {"s": "sportmaster-krossovki-muzhskie-fila", "t": "Мужские кроссовки Fila в Спортмастере: гид по моделям и выбору", "i": "🏠", "c": "byt-i-khobbi"}, {"s": "spt-eto-v-mchs", "t": "СПТ в МЧС: расшифровка, функции и отличия от пожарных", "i": "📁", "c": "drugoe"}, {"s": "spisok-dlya-poezdki-v-drugoj-gorod", "t": "Список для поездки в другой город: что взять и не забыть", "i": "🏠", "c": "byt-i-khobbi"}, {"s": "sportivnye-mashiny-dlya-goroda", "t": "Спортивные машины для города: выбор, нюансы и лучшие модели", "i": "📁", "c": null}, {"s": "sposoby-dostavit-udovolstvie-muzhchine", "t": "Как доставить удовольствие мужчине: психология и секреты", "i": "📁", "c": "drugoe"}, {"s": "spas-odeyalo-chto-eto", "t": "Спас-одеяло: что это, как работает и где применяется", "i": "🛡️", "c": "bezopasnost"}, {"s": "spetsialist-po-vykupu-avtomobilej-s-probegom", "t": "Специалист по выкупу автомобилей: кто это и зачем нужен", "i": "📁", "c": null}, {"s": "spetsifikatsiya-avto-po-vin", "t": "Спецификация авто по VIN: как узнать комплектацию и коды", "i": "📁", "c": null}, {"s": "spravka-ob-utilizatsii-ts", "t": "Справка об утилизации ТС: получение, сроки, Госуслуги", "i": "⚖️", "c": "zakony-i-pdd"}, {"s": "spokojstviya-i-umirotvoreniya-ot-sliyaniya-vechnogo-i-beskonechnogo-tekst", "t": "Слияние вечного и бесконечного: путь к умиротворению", "i": "🏠", "c": "byt-i-khobbi"}, {"s": "spravka-iz-gibdd-o-snyatii-ts-s-ucheta", "t": "Справка из ГИБДД о снятии с учета: сроки, образцы и порядок действий", "i": "⚖️", "c": "zakony-i-pdd"}, {"s": "sprej-ot-gryzunov-dlya-avto", "t": "Спрей от грызунов для авто: рейтинг лучших средств и защита проводки", "i": "🧼", "c": "ukhod-i-mojka"}, {"s": "spisok-chto-nuzhno-vzyat-s-soboj-v-poezdku", "t": "Список что нужно взять в поездку: чек-лист вещей и документов", "i": "🏠", "c": "byt-i-khobbi"}, {"s": "spas-na-krovi-skolko-stroilsya", "t": "Спас на Крови: сколько строился собор в Санкт-Петербурге", "i": "📜", "c": "istoriya-i-fakty"}, {"s": "spisok-nomerov-amr-komu-prinadlezhat", "t": "Кому принадлежат номера AMR: расшифровка кода региона", "i": "⚖️", "c": "zakony-i-pdd"}, {"s": "spidometr-dlya-avtomobilya-tsifrovoj-kupit", "t": "Цифровой спидометр для автомобиля: какой купить и как выбрать", "i": "📱", "c": "tekhnika-i-gadzhety"}, {"s": "spravka-ob-otsutstvii-ts-cherez-gosuslugi", "t": "Справка об отсутствии ТС через Госуслуги: пошаговая инструкция", "i": "⚖️", "c": "zakony-i-pdd"}, {"s": "spisok-stran-s-pravostoronnim-dvizheniem", "t": "Список стран с правосторонним движением: полный гид для автопутешественников", "i": "⚖️", "c": "zakony-i-pdd"}, {"s": "sprej-dlya-zashchity-kontaktov-ot-vlagi", "t": "Спрей для защиты контактов от влаги: выбор и применение", "i": "⚡", "c": "elektrika-avto"}, {"s": "sprej-okhladitel-dlya-metalla", "t": "Спрей охладитель для металла: выбор, применение и свойства", "i": "🏗️", "c": "garazh-master"}, {"s": "spasitelnaya-fortochka-8-bukv", "t": "Загадка «спасительная форточка» 8 букв: ответы и смысл", "i": "📁", "c": "drugoe"}, {"s": "sport-spetsnaza-5-bukv", "t": "Спорт спецназа 5 букв: разгадка кроссворда и реальная подготовка", "i": "🛡️", "c": "bezopasnost"}, {"s": "spalnyj-meshok-s-podogrevom-ot-pauerbanka", "t": "Спальный мешок с подогревом от пауэрбанка: выбор и обзор", "i": "📱", "c": "tekhnika-i-gadzhety"}, {"s": "spisok-radiostantsij-yandeks-stantsii", "t": "Список радиостанций Яндекс Станции: полный каталог и поиск", "i": "📱", "c": "tekhnika-i-gadzhety"}, {"s": "sposoby-uvelicheniya-gruzopodemnosti-avtomobilya", "t": "Как увеличить грузоподъемность автомобиля: методы и риски", "i": "🎨", "c": "tyuning-i-stil"}, {"s": "spisok-veshchej-v-poezdku-v-drugoj-gorod-na-3-dnya", "t": "Список вещей в поездку на 3 дня: полный чек-лист", "i": "🏠", "c": "byt-i-khobbi"}, {"s": "sprej-antidozhd-dlya-stekol-avtomobilya", "t": "Спрей антидождь для стекол: полный обзор и инструкция", "i": "🧼", "c": "ukhod-i-mojka"}, {"s": "spisok-dokumentov-dlya-postanovki-na-uchet-avtomobilya-yuridicheskim-litsom", "t": "Документы для регистрации авто на юрлицо: полный список 2026", "i": "⚖️", "c": "zakony-i-pdd"}, {"s": "spetsklyuch-dlya-snyatiya-rulevoj-tyagi", "t": "Спецключ для снятия рулевой тяги: выбор, виды и применение", "i": "🏗️", "c": "garazh-master"}, {"s": "splen-chto-eto-takoe", "t": "Сплэн: что это такое, функции органа и болезни", "i": "🍷", "c": "voditel-i-zdorove"}, {"s": "spirtnoe-v-pyaterochke-katalog-i-tseny", "t": "Спиртное в Пятерочке: актуальный каталог и цены", "i": "🏠", "c": "byt-i-khobbi"}, {"s": "sprej-keramika-dlya-avto", "t": "Спрей-керамика для авто: выбор, нанесение и эффект", "i": "🧼", "c": "ukhod-i-mojka"}, {"s": "spalnik-na-kryshu-legkovogo-avtomobilya", "t": "Спальник на крышу авто: выбор, установка и безопасность", "i": "🏠", "c": "byt-i-khobbi"}, {"s": "sport-avto-vologda-katalog", "t": "Спорт авто Вологда: каталог, цены и выбор", "i": "📁", "c": null}, {"s": "spisok-dokumentov-pri-registratsii-avtomobilya", "t": "Документы для регистрации авто: полный список 2026", "i": "⚖️", "c": "zakony-i-pdd"}, {"s": "sportivno-rybolovnaya-baza-parus-sever", "t": "База Парус Север: рыбалка, цены и услуги 2026", "i": "🏠", "c": "byt-i-khobbi"}, {"s": "sposoby-krepleniya-detskogo-avtokresla", "t": "Крепление детского автокресла: Isofix и ремень", "i": "🛡️", "c": "bezopasnost"}, {"s": "sportivnoe-sidene-dlya-avtomobilya", "t": "Спортивное сиденье: выбор, установка и безопасность", "i": "🎨", "c": "tyuning-i-stil"}, {"s": "spisat-avtomobil-s-balansa-organizatsii", "t": "Как списать автомобиль с баланса организации: пошаговая инструкция", "i": "⚖️", "c": "zakony-i-pdd"}, {"s": "sposob-tyuninga-avtomobilya-5-bukv-skanvord", "t": "Способ тюнинга автомобиля 5 букв: ответы сканвордов и реальные методы", "i": "🎨", "c": "tyuning-i-stil"}, {"s": "sparco-perchatki-dlya-avtosporta", "t": "Перчатки Sparco для автоспорта: обзор, выбор и уход", "i": "🛡️", "c": "bezopasnost"}, {"s": "spelaya-vishnya-tsvet-avto", "t": "Вишнёвый цвет авто: психология, покраска и уход за кузовом", "i": "🎨", "c": "tyuning-i-stil"}, {"s": "sportivnaya-mashina-s-loshadyu", "t": "Спортивная машина с лошадью: ТОП-5 мощных авто", "i": "🎨", "c": "tyuning-i-stil"}, {"s": "spravochnaya-po-evakuatsii-mashin", "t": "Справочная по эвакуации машин: куда звонить, тарифы, права", "i": "⚖️", "c": "zakony-i-pdd"}, {"s": "sprej-dlya-snyatiya-nakleek", "t": "Спрей для снятия наклеек: лучший удалитель клея с авто", "i": "🧼", "c": "ukhod-i-mojka"}, {"s": "spb-vladimir-rasstoyanie-na-mashine", "t": "Расстояние от СПб до Владимира на машине: маршрут и время", "i": "⚖️", "c": "zakony-i-pdd"}, {"s": "sports-ru-devushka-dnya", "t": "Спортс ру девушка дня: как стать моделью и попасть на фото", "i": "🎨", "c": "tyuning-i-stil"}, {"s": "spisok-kitajskikh-mashin-na-rossijskom-rynke", "t": "Список китайских машин на российском рынке: актуальный обзор 2026", "i": "📁", "c": null}, {"s": "spisok-mashin-iz-forsazha", "t": "Список машин из Форсажа: все авто франшизы Fast & Furious", "i": "📜", "c": "istoriya-i-fakty"}, {"s": "spravka-o-raskhode-topliva-avtomobilya-gde-vzyat", "t": "Где взять справку о расходе топлива: все способы получения", "i": "⚖️", "c": "zakony-i-pdd"}, {"s": "spets-antenna-na-avto", "t": "Спец антенна на авто: выбор, установка и настройка СВ радиостанции", "i": "⚡", "c": "elektrika-avto"}, {"s": "spisok-dokumentov-dlya-registratsii-avtomobilya-v-gibdd-dlya-yuridicheskikh-lits", "t": "Документы для регистрации авто в ГИБДД для юридических лиц", "i": "⚖️", "c": "zakony-i-pdd"}, {"s": "spravka-o-probege-avtomobilya", "t": "Справка о пробеге автомобиля: где взять и как проверить", "i": "⚖️", "c": "zakony-i-pdd"}, {"s": "spasatelnoe-pokryvalo-kakoj-storonoj-k-telu", "t": "Спасательное покрывало: какой стороной к телу и как использовать", "i": "🛡️", "c": "bezopasnost"}, {"s": "spb-vladimir-kak-dobratsya", "t": "Как добраться из СПб во Владимир: все способы и цены", "i": "📁", "c": "drugoe"}, {"s": "spisok-dokumentov-v-gai-dlya-postanovki-na-uchet-avtomobilya", "t": "Документы в ГАИ для регистрации авто: полный список 2026", "i": "⚖️", "c": "zakony-i-pdd"}, {"s": "spisok-avto-gta-sa", "t": "Полный список авто GTA SA: характеристики, спид-лист и секреты", "i": "📜", "c": "istoriya-i-fakty"}, {"s": "spetsialist-po-podboru-avtomobilej-s-probegom", "t": "Специалист по подбору авто: как выбрать эксперта для покупки", "i": "📁", "c": null}, {"s": "spisok-mashin-gran-turismo-7", "t": "Список машин Gran Turismo 7: полный каталог и автодромы", "i": "🏠", "c": "byt-i-khobbi"}, {"s": "spasatelnoe-odeyalo-izotermicheskoe-kak-polzovatsya", "t": "Спасательное изотермическое одеяло: как правильно пользоваться", "i": "🛡️", "c": "bezopasnost"}, {"s": "spisok-chto-vzyat-s-soboj-v-dorogu", "t": "Что взять в дорогу: полный список вещей для автопутешествия", "i": "🏠", "c": "byt-i-khobbi"}, {"s": "spisok-lekarstvennykh-sredstv-zapreshchennykh-dlya-voditelej", "t": "Запрещенные лекарства для водителей: полный список 2026", "i": "⚖️", "c": "zakony-i-pdd"}, {"s": "sposoby-soedineniya-provodov-v-avtomobile", "t": "Способы соединения проводов в автомобиле: пайка, скрутка, клеммы", "i": "⚡", "c": "elektrika-avto"}, {"s": "spas-na-krovi-vid-sverkhu", "t": "Храм Спаса на Крови: вид сверху, панорама и история", "i": "📜", "c": "istoriya-i-fakty"}, {"s": "spetsialist-po-pokupke-avto", "t": "Специалист по покупке авто: зачем нужен и что проверяет эксперт", "i": "📁", "c": null}, {"s": "spokojstviya-umirotvoreniya-i-garmonii-ot-sliyaniya-s-beskonechnym-vechnym", "t": "Гармония и умиротворение: путь к слиянию с вечным", "i": "📁", "c": "drugoe"}, {"s": "sprava-obgonyaet-gruzovik-kak-pishetsya", "t": "Правила обгона грузовика справа: законно или штраф?", "i": "⚖️", "c": "zakony-i-pdd"}, {"s": "sprej-dlya-remnya-grm", "t": "Спрей для ремня ГРМ: стоит ли использовать или вред для двигателя?", "i": "🛢️", "c": "zapchasti-i-masla"}, {"s": "spring-trap-iz-plastilina", "t": "Спринг-трап из пластилина: делаем ловушку своими руками", "i": "🏠", "c": "byt-i-khobbi"}, {"s": "spin-perevod-na-russkij-na-stiralnoj-mashine-bosch", "t": "Spin на стиральной машине Bosch: перевод и расшифровка", "i": "🏠", "c": "byt-i-khobbi"}, {"s": "spg-eto-metan-ili-propan", "t": "СПГ это метан или пропан: Разница, свойства и применение в авто", "i": "🛢️", "c": "zapchasti-i-masla"}, {"s": "spisok-mashin-v-gta-san-andreas-na-eksport", "t": "Список машин в GTA San Andreas на экспорт: ТОП-10 авто", "i": "🎨", "c": "tyuning-i-stil"}, {"s": "split-bolt-dlya-soedineniya-provodov", "t": "Сплит болт для соединения проводов: виды, монтаж и применение", "i": "⚡", "c": "elektrika-avto"}, {"s": "spravka-ob-utilizatsii-avtomobilya-dlya-gibdd-gde-poluchit", "t": "Справка об утилизации автомобиля для ГИБДД: где получить в 2026 году", "i": "⚖️", "c": "zakony-i-pdd"}, {"s": "spisok-avtomobilej-gran-turismo-7", "t": "Список автомобилей Gran Turismo 7: Полный каталог и классификация", "i": "🏠", "c": "byt-i-khobbi"}, {"s": "spravka-iz-gai-ob-otsutstvii-transportnogo-sredstva-cherez-gosuslugi", "t": "Справка из ГАИ об отсутствии ТС через Госуслуги: пошагово", "i": "⚖️", "c": "zakony-i-pdd"}, {"s": "spisok-dokumentov-dlya-pereoformleniya-avtomobilya", "t": "Список документов для переоформления автомобиля 2026: полный перечень", "i": "⚖️", "c": "zakony-i-pdd"}, {"s": "sport-avto-vologda-servis", "t": "Спорт Авто Вологда Сервис: Профессиональный ремонт и тюнинг", "i": "📁", "c": null}, {"s": "sport-avto-vologda-avtoservis", "t": "Спорт Авто Вологда: Профессиональный автосервис и тюнинг", "i": "🏗️", "c": "garazh-master"}, {"s": "sport-avto-vologda-ilyushina-telefon", "t": "Спорт-авто Вологда: Ильюшина, автосалоны и контакты", "i": "📁", "c": null}, {"s": "speed-perfect-na-stiralnoj-mashine-bosch", "t": "Speed Perfect на стиральной машине Bosch: что это и когда включать", "i": "🏠", "c": "byt-i-khobbi"}, {"s": "spisok-bukv-na-nomerakh-mashin", "t": "Список букв на номерах машин: что значат и как выбрать", "i": "⚖️", "c": "zakony-i-pdd"}, {"s": "spisok-veshchej-chto-vzyat-s-soboj-v-poezdku", "t": "Список вещей в поездку: чек-лист на все случаи", "i": "📁", "c": "drugoe"}, {"s": "spisok-veshchej-na-nedelyu-v-drugoj-gorod", "t": "Список вещей на неделю в другой город: полный чек-лист", "i": "🏠", "c": "byt-i-khobbi"}, {"s": "sportkary-do-1-mln", "t": "Лучшие спорткары до 1 млн рублей: выбор, риски и модели", "i": "📁", "c": null}, {"s": "spravka-iz-gibdd-o-nalichii-transportnogo-sredstva-cherez-gosuslugi", "t": "Справка из ГИБДД о наличии ТС через Госуслуги: инструкция", "i": "⚖️", "c": "zakony-i-pdd"}, {"s": "spisok-neobkhodimykh-veshchej-v-poezdku", "t": "Список необходимых вещей в поездку: полный чек-лист", "i": "🏠", "c": "byt-i-khobbi"}, {"s": "spravka-o-prekrashchenii-registratsii-transportnogo-sredstva", "t": "Справка о прекращении регистрации ТС: как получить и зачем", "i": "⚖️", "c": "zakony-i-pdd"}, {"s": "spalnyj-boks-na-kryshu-gruzovika", "t": "Спальный бокс на крышу грузовика: установка, виды, выбор", "i": "🚜", "c": "spetstekhnika-i-moto"}, {"s": "spas-na-krovi-dejstvuyushchij-khram", "t": "Храм Спаса на Крови: действующий или музей? История и режим работы", "i": "📜", "c": "istoriya-i-fakty"}, {"s": "spisanie-utilsbora-na-avtomobili", "t": "Списание утильсбора на автомобили: кто освобожден в 2026 году", "i": "⚖️", "c": "zakony-i-pdd"}, {"s": "spisok-rabot-v-avtoservise", "t": "Список работ в автосервисе: что входит и как проверяют", "i": "🏗️", "c": "garazh-master"}, {"s": "spb-sobor-spas-na-krovi", "t": "Собор Спаса на Крови в СПб: история, режим работы и цены 2026", "i": "📁", "c": "drugoe"}, {"s": "spisok-veshchej-v-poezdku-na-nedelyu-v-drugoj-gorod", "t": "Список вещей в поездку на неделю: чек-лист и советы", "i": "🏠", "c": "byt-i-khobbi"}, {"s": "sportivnye-polotentsa-iz-mikrofibry-otzyvy", "t": "Спортивные полотенца из микрофибры: отзывы и рейтинг 2026", "i": "🏠", "c": "byt-i-khobbi"}, {"s": "spirtovoj-rastvor-dlya-oklejki-plenki-na-avto", "t": "Спиртовой раствор для оклейки пленки на авто: рецепт и применение", "i": "🎨", "c": "tyuning-i-stil"}, {"s": "spas-na-krovi-skolko-kupolov", "t": "Сколько куполов у храма Спаса на Крови: детали и история", "i": "📜", "c": "istoriya-i-fakty"}, {"s": "sportivnye-mashiny-do-2-mln", "t": "Спортивные машины до 2 млн рублей: топ-10 лучших купе и хэтчбеков", "i": "📁", "c": null}, {"s": "sposob-postanovki-transportnogo-sredstva-na-stoyanku-tablichki-s-kommentariyami", "t": "Табличка «Стоянка запрещена»: разбор знаков и штрафов", "i": "⚖️", "c": "zakony-i-pdd"}, {"s": "spravka-ob-otsutstvii-avtomobilya-v-sobstvennosti-gosuslugi-kak-poluchit", "t": "Справка об отсутствии авто: как получить на Госуслугах", "i": "⚖️", "c": "zakony-i-pdd"}, {"s": "spisok-veshchej-na-3-dnya-v-drugoj-gorod", "t": "Список вещей на 3 дня в другой город: чек-лист", "i": "📁", "c": "drugoe"}, {"s": "splin-davajte-delat-pauzy-v-slovakh-akkordy", "t": "Аккорды Сплин: Давайте делать паузы", "i": "🏠", "c": "byt-i-khobbi"}, {"s": "spokojnaya-muzyka-v-avto", "t": "Спокойная музыка в авто: лучший саундтрек для расслабленной езды", "i": "🍷", "c": "voditel-i-zdorove"}, {"s": "sport-s-mashinami-kak-nazyvaetsya", "t": "Как называется спорт с машинами: виды автоспорта", "i": "📁", "c": "drugoe"}, {"s": "sport-pasport-na-avto", "t": "Спорт паспорт на авто: как сделать и где получить", "i": "🎨", "c": "tyuning-i-stil"}, {"s": "sprej-klej-dlya-tkani-potolka-avtomobilya", "t": "Спрей-клей для потолка авто: выбор и применение", "i": "🧼", "c": "ukhod-i-mojka"}, {"s": "sportivnye-kresla-v-mashinu", "t": "Спортивные кресла в машину: выбор, установка и безопасность", "i": "🎨", "c": "tyuning-i-stil"}, {"s": "sposob-postanovki-avtomobilya-na-stoyanku", "t": "Способы постановки автомобиля на стоянку: инструкции и ПДД", "i": "🎓", "c": "obuchenie-vozhdeniyu"}, {"s": "spidometr-na-korable-3-bukvy", "t": "Спидометр на корабле 3 буквы: Лаг, Узел, Фут? Ответ и термины", "i": "📁", "c": "drugoe"}, {"s": "spisok-avtomobilej-nalog-na-roskosh-2024", "t": "Список автомобилей налог на роскошь 2026: актуальные модели", "i": "⚖️", "c": "zakony-i-pdd"}, {"s": "sport-avto-vologda-ilyushina-rezhim-raboty", "t": "Спорт Авто Вологда на Ильюшина: режим работы и контакты", "i": "📁", "c": null}]